{
  "args": {
    "max_level": 2,
    "response_mode": "power_saturating",
    "source": "live",
    "transverse_amp": 0.42,
    "nonlinear_gamma": 1.65,
    "nonlinear_threshold": 1.8,
    "cascade_A_threshold": 0.18,
    "cascade_gamma": 1.75,
    "cascade_transverse_gamma": 1.25,
    "transverse_nonlinear_weight": 1.4,
    "directed_nonlinear_weight": 1.1,
    "cascade_fatigue": 0.25,
    "cascade_rescan": true,
    "allow_reuse_faces": false,
    "allow_quotient": false,
    "max_boundary_faces": 90,
    "max_single_vertices": 12,
    "max_pair_candidates": 2200,
    "max_rows": 4400,
    "max_auto_pairings": 2,
    "max_cascade_per_birth": 2,
    "min_tets_before_pairing": 4,
    "min_birth_time_before_pairing": 4,
    "min_nonlinear_score": 0.0,
    "keep_top_candidates": 160,
    "max_eval_candidates": 0,
    "only_A_gate": true,
    "antisym_eta": 1.0,
    "erase_phase_for_strict_sym": true,
    "lock_residual_threshold": 0.2,
    "lock_max_threshold": 0.3,
    "variants": [
      "real_growth",
      "strict_symmetrized_control",
      "no_backreaction"
    ],
    "phase_signs": [
      1,
      -1
    ],
    "out": "C_eigen_quadrature_refinement_out_L2",
    "zip": "/mnt/data/cnna62_work/cnna_C_eigen_quadrature_refinement_gate_pkg_L2.zip"
  },
  "variant_rows": [
    {
      "variant": "real_growth",
      "variant_phase": "real_growth_phaseplus1",
      "phase_sign": 1,
      "max_level": 2,
      "source": "live",
      "baseline_metrics": {
        "vertices": 13,
        "edges": 33,
        "faces": 31,
        "tets": 10,
        "euler": 1,
        "beta0": 1,
        "beta1": 0,
        "beta2": 0,
        "beta3": 0,
        "boundary_faces": 22,
        "saturated_faces": 9,
        "overfull_faces": 0,
        "boundary_fraction": 0.7096774193548159,
        "saturated_fraction": 0.29032258064515193,
        "manifold_face_fraction": 0.9999999999999678,
        "edge_link_cycle_count": 0,
        "edge_link_candidate_count": 17,
        "edge_link_cycle_fraction": 0.0,
        "edge_link_noncircle_cycle_count": 0,
        "K_mean": 0.8073735822465625,
        "K_p95": 1.8499405472778678,
        "closed_ratio": 0.4594816320937747,
        "exact_residual_ratio": 0.2571057228705153,
        "harmonic_ratio": 0.0
      },
      "auto_metrics": {
        "vertices": 13,
        "edges": 38,
        "faces": 44,
        "tets": 16,
        "euler": 3,
        "beta0": 1,
        "beta1": 0,
        "beta2": 2,
        "beta3": 0,
        "boundary_faces": 24,
        "saturated_faces": 20,
        "overfull_faces": 0,
        "boundary_fraction": 0.545454545454533,
        "saturated_fraction": 0.4545454545454442,
        "manifold_face_fraction": 0.9999999999999772,
        "edge_link_cycle_count": 4,
        "edge_link_candidate_count": 27,
        "edge_link_cycle_fraction": 0.14814814814814267,
        "edge_link_noncircle_cycle_count": 0,
        "K_mean": 0.7146784788084811,
        "K_p95": 1.5429561887612795,
        "closed_ratio": 0.5210793707852407,
        "exact_residual_ratio": 0.2750951577609177,
        "harmonic_ratio": 0.12161711213082593
      },
      "automatic_pairings_applied": 2,
      "automatic_pairing_attempts_logged": 2,
      "candidate_refinement_metrics": {
        "candidate_count_ok": 13,
        "candidate_count_beta2_opening": 9,
        "candidate_count_selected_by_rule": 2,
        "candidate_count_beta2_and_C_eigen_lock": 1,
        "exists_beta2_and_C_eigen_lock": true,
        "best_all_C_eigen_lock_mean": 0.13800603779333703,
        "best_all_C_eigen_lock_max": 0.13800603779333967,
        "best_all_delta_beta2": 2,
        "best_all_candidate_id": 32,
        "best_beta2_C_eigen_lock_mean": 0.13800603779333703,
        "best_beta2_C_eigen_lock_max": 0.13800603779333967,
        "best_beta2_candidate_id": 32,
        "best_beta2_selected_by_current_rule": false,
        "best_beta2_transport_cosine": -0.06027679987050255,
        "best_beta2_directed_imbalance": 0.47978443481550515,
        "best_beta2_transverse_complementarity": 0.33612090443309484,
        "best_beta2_comm_signed_birth_over_abs": -0.20417768143318046,
        "selected_C_eigen_lock_mean": 0.28878626181577566,
        "selected_C_eigen_lock_max": 0.28878626181580047,
        "selected_transport_cosine_mean": -0.21428636706750248,
        "beta2_transport_cosine_mean": 0.2644592295862268,
        "beta2_C_eigen_lock_mean_mean": 0.44059215075733926,
        "beta2_comm_signed_birth_over_abs_mean": -0.07734225295922531
      },
      "interpretation_flags": {
        "beta2_opened_by_current_rule": true,
        "exists_beta2_and_C_eigen_lock": true,
        "current_rule_missed_better_beta2_candidate": true,
        "decision_used_delta_beta_any": false
      }
    },
    {
      "variant": "real_growth",
      "variant_phase": "real_growth_phaseminus1",
      "phase_sign": -1,
      "max_level": 2,
      "source": "live",
      "baseline_metrics": {
        "vertices": 13,
        "edges": 33,
        "faces": 31,
        "tets": 10,
        "euler": 1,
        "beta0": 1,
        "beta1": 0,
        "beta2": 0,
        "beta3": 0,
        "boundary_faces": 22,
        "saturated_faces": 9,
        "overfull_faces": 0,
        "boundary_fraction": 0.7096774193548159,
        "saturated_fraction": 0.29032258064515193,
        "manifold_face_fraction": 0.9999999999999678,
        "edge_link_cycle_count": 0,
        "edge_link_candidate_count": 17,
        "edge_link_cycle_fraction": 0.0,
        "edge_link_noncircle_cycle_count": 0,
        "K_mean": 0.8073735822465625,
        "K_p95": 1.8499405472778678,
        "closed_ratio": 0.4594816320937747,
        "exact_residual_ratio": 0.2571057228705153,
        "harmonic_ratio": 0.0
      },
      "auto_metrics": {
        "vertices": 13,
        "edges": 38,
        "faces": 44,
        "tets": 16,
        "euler": 3,
        "beta0": 1,
        "beta1": 0,
        "beta2": 2,
        "beta3": 0,
        "boundary_faces": 24,
        "saturated_faces": 20,
        "overfull_faces": 0,
        "boundary_fraction": 0.545454545454533,
        "saturated_fraction": 0.4545454545454442,
        "manifold_face_fraction": 0.9999999999999772,
        "edge_link_cycle_count": 4,
        "edge_link_candidate_count": 27,
        "edge_link_cycle_fraction": 0.14814814814814267,
        "edge_link_noncircle_cycle_count": 0,
        "K_mean": 0.7146784788084811,
        "K_p95": 1.5429561887612795,
        "closed_ratio": 0.5210793707852407,
        "exact_residual_ratio": 0.2750951577609177,
        "harmonic_ratio": 0.12161711213082593
      },
      "automatic_pairings_applied": 2,
      "automatic_pairing_attempts_logged": 2,
      "candidate_refinement_metrics": {
        "candidate_count_ok": 13,
        "candidate_count_beta2_opening": 9,
        "candidate_count_selected_by_rule": 2,
        "candidate_count_beta2_and_C_eigen_lock": 1,
        "exists_beta2_and_C_eigen_lock": true,
        "best_all_C_eigen_lock_mean": 0.17309180304906585,
        "best_all_C_eigen_lock_max": 0.17309180304907085,
        "best_all_delta_beta2": 2,
        "best_all_candidate_id": 32,
        "best_beta2_C_eigen_lock_mean": 0.17309180304906585,
        "best_beta2_C_eigen_lock_max": 0.17309180304907085,
        "best_beta2_candidate_id": 32,
        "best_beta2_selected_by_current_rule": false,
        "best_beta2_transport_cosine": 0.19267692094939406,
        "best_beta2_directed_imbalance": 0.47978443481550515,
        "best_beta2_transverse_complementarity": 0.33612090443309484,
        "best_beta2_comm_signed_birth_over_abs": -0.1841567457887425,
        "selected_C_eigen_lock_mean": 0.2129405886765075,
        "selected_C_eigen_lock_max": 0.21294058867652324,
        "selected_transport_cosine_mean": 0.2688131842226834,
        "beta2_transport_cosine_mean": 0.3318886746234179,
        "beta2_C_eigen_lock_mean_mean": 0.4939193733526359,
        "beta2_comm_signed_birth_over_abs_mean": -0.04308355506558064
      },
      "interpretation_flags": {
        "beta2_opened_by_current_rule": true,
        "exists_beta2_and_C_eigen_lock": true,
        "current_rule_missed_better_beta2_candidate": true,
        "decision_used_delta_beta_any": false
      }
    },
    {
      "variant": "strict_symmetrized_control",
      "variant_phase": "strict_symmetrized_control_phaseplus1",
      "phase_sign": 1,
      "max_level": 2,
      "source": "live",
      "baseline_metrics": {
        "vertices": 13,
        "edges": 33,
        "faces": 31,
        "tets": 10,
        "euler": 1,
        "beta0": 1,
        "beta1": 0,
        "beta2": 0,
        "beta3": 0,
        "boundary_faces": 22,
        "saturated_faces": 9,
        "overfull_faces": 0,
        "boundary_fraction": 0.7096774193548159,
        "saturated_fraction": 0.29032258064515193,
        "manifold_face_fraction": 0.9999999999999678,
        "edge_link_cycle_count": 0,
        "edge_link_candidate_count": 17,
        "edge_link_cycle_fraction": 0.0,
        "edge_link_noncircle_cycle_count": 0,
        "K_mean": 0.32140402279565433,
        "K_p95": 0.6893765035318247,
        "closed_ratio": 0.42774555855357127,
        "exact_residual_ratio": 0.22251224848593212,
        "harmonic_ratio": 0.0
      },
      "auto_metrics": {
        "vertices": 13,
        "edges": 33,
        "faces": 31,
        "tets": 10,
        "euler": 1,
        "beta0": 1,
        "beta1": 0,
        "beta2": 0,
        "beta3": 0,
        "boundary_faces": 22,
        "saturated_faces": 9,
        "overfull_faces": 0,
        "boundary_fraction": 0.7096774193548159,
        "saturated_fraction": 0.29032258064515193,
        "manifold_face_fraction": 0.9999999999999678,
        "edge_link_cycle_count": 0,
        "edge_link_candidate_count": 17,
        "edge_link_cycle_fraction": 0.0,
        "edge_link_noncircle_cycle_count": 0,
        "K_mean": 0.32140402279565433,
        "K_p95": 0.6893765035318247,
        "closed_ratio": 0.42774555855357127,
        "exact_residual_ratio": 0.22251224848593212,
        "harmonic_ratio": 0.0
      },
      "automatic_pairings_applied": 0,
      "automatic_pairing_attempts_logged": 0,
      "candidate_refinement_metrics": {
        "candidate_count_ok": 0,
        "candidate_count_beta2_opening": 0,
        "candidate_count_selected_by_rule": 0,
        "candidate_count_beta2_and_C_eigen_lock": 0,
        "exists_beta2_and_C_eigen_lock": false,
        "best_all_C_eigen_lock_mean": 0.0,
        "best_all_C_eigen_lock_max": 0.0,
        "best_all_delta_beta2": "",
        "best_all_candidate_id": "",
        "best_beta2_C_eigen_lock_mean": 0.0,
        "best_beta2_C_eigen_lock_max": 0.0,
        "best_beta2_candidate_id": "",
        "best_beta2_selected_by_current_rule": false,
        "best_beta2_transport_cosine": 0.0,
        "best_beta2_directed_imbalance": 0.0,
        "best_beta2_transverse_complementarity": 0.0,
        "best_beta2_comm_signed_birth_over_abs": 0.0,
        "selected_C_eigen_lock_mean": 0.0,
        "selected_C_eigen_lock_max": 0.0,
        "selected_transport_cosine_mean": 0.0,
        "beta2_transport_cosine_mean": 0.0,
        "beta2_C_eigen_lock_mean_mean": 0.0,
        "beta2_comm_signed_birth_over_abs_mean": 0.0
      },
      "interpretation_flags": {
        "beta2_opened_by_current_rule": false,
        "exists_beta2_and_C_eigen_lock": false,
        "current_rule_missed_better_beta2_candidate": false,
        "decision_used_delta_beta_any": false
      }
    },
    {
      "variant": "strict_symmetrized_control",
      "variant_phase": "strict_symmetrized_control_phaseminus1",
      "phase_sign": -1,
      "max_level": 2,
      "source": "live",
      "baseline_metrics": {
        "vertices": 13,
        "edges": 33,
        "faces": 31,
        "tets": 10,
        "euler": 1,
        "beta0": 1,
        "beta1": 0,
        "beta2": 0,
        "beta3": 0,
        "boundary_faces": 22,
        "saturated_faces": 9,
        "overfull_faces": 0,
        "boundary_fraction": 0.7096774193548159,
        "saturated_fraction": 0.29032258064515193,
        "manifold_face_fraction": 0.9999999999999678,
        "edge_link_cycle_count": 0,
        "edge_link_candidate_count": 17,
        "edge_link_cycle_fraction": 0.0,
        "edge_link_noncircle_cycle_count": 0,
        "K_mean": 0.32140402279565433,
        "K_p95": 0.6893765035318247,
        "closed_ratio": 0.42774555855357127,
        "exact_residual_ratio": 0.22251224848593212,
        "harmonic_ratio": 0.0
      },
      "auto_metrics": {
        "vertices": 13,
        "edges": 33,
        "faces": 31,
        "tets": 10,
        "euler": 1,
        "beta0": 1,
        "beta1": 0,
        "beta2": 0,
        "beta3": 0,
        "boundary_faces": 22,
        "saturated_faces": 9,
        "overfull_faces": 0,
        "boundary_fraction": 0.7096774193548159,
        "saturated_fraction": 0.29032258064515193,
        "manifold_face_fraction": 0.9999999999999678,
        "edge_link_cycle_count": 0,
        "edge_link_candidate_count": 17,
        "edge_link_cycle_fraction": 0.0,
        "edge_link_noncircle_cycle_count": 0,
        "K_mean": 0.32140402279565433,
        "K_p95": 0.6893765035318247,
        "closed_ratio": 0.42774555855357127,
        "exact_residual_ratio": 0.22251224848593212,
        "harmonic_ratio": 0.0
      },
      "automatic_pairings_applied": 0,
      "automatic_pairing_attempts_logged": 0,
      "candidate_refinement_metrics": {
        "candidate_count_ok": 0,
        "candidate_count_beta2_opening": 0,
        "candidate_count_selected_by_rule": 0,
        "candidate_count_beta2_and_C_eigen_lock": 0,
        "exists_beta2_and_C_eigen_lock": false,
        "best_all_C_eigen_lock_mean": 0.0,
        "best_all_C_eigen_lock_max": 0.0,
        "best_all_delta_beta2": "",
        "best_all_candidate_id": "",
        "best_beta2_C_eigen_lock_mean": 0.0,
        "best_beta2_C_eigen_lock_max": 0.0,
        "best_beta2_candidate_id": "",
        "best_beta2_selected_by_current_rule": false,
        "best_beta2_transport_cosine": 0.0,
        "best_beta2_directed_imbalance": 0.0,
        "best_beta2_transverse_complementarity": 0.0,
        "best_beta2_comm_signed_birth_over_abs": 0.0,
        "selected_C_eigen_lock_mean": 0.0,
        "selected_C_eigen_lock_max": 0.0,
        "selected_transport_cosine_mean": 0.0,
        "beta2_transport_cosine_mean": 0.0,
        "beta2_C_eigen_lock_mean_mean": 0.0,
        "beta2_comm_signed_birth_over_abs_mean": 0.0
      },
      "interpretation_flags": {
        "beta2_opened_by_current_rule": false,
        "exists_beta2_and_C_eigen_lock": false,
        "current_rule_missed_better_beta2_candidate": false,
        "decision_used_delta_beta_any": false
      }
    },
    {
      "variant": "no_backreaction",
      "variant_phase": "no_backreaction_phaseplus1",
      "phase_sign": 1,
      "max_level": 2,
      "source": "live",
      "baseline_metrics": {
        "vertices": 13,
        "edges": 33,
        "faces": 31,
        "tets": 10,
        "euler": 1,
        "beta0": 1,
        "beta1": 0,
        "beta2": 0,
        "beta3": 0,
        "boundary_faces": 22,
        "saturated_faces": 9,
        "overfull_faces": 0,
        "boundary_fraction": 0.7096774193548159,
        "saturated_fraction": 0.29032258064515193,
        "manifold_face_fraction": 0.9999999999999678,
        "edge_link_cycle_count": 0,
        "edge_link_candidate_count": 17,
        "edge_link_cycle_fraction": 0.0,
        "edge_link_noncircle_cycle_count": 0,
        "K_mean": 0.6243169724281119,
        "K_p95": 1.3870186003895344,
        "closed_ratio": 0.5081210545386275,
        "exact_residual_ratio": 0.2737836843813679,
        "harmonic_ratio": 0.0
      },
      "auto_metrics": {
        "vertices": 13,
        "edges": 38,
        "faces": 44,
        "tets": 16,
        "euler": 3,
        "beta0": 1,
        "beta1": 0,
        "beta2": 2,
        "beta3": 0,
        "boundary_faces": 24,
        "saturated_faces": 20,
        "overfull_faces": 0,
        "boundary_fraction": 0.545454545454533,
        "saturated_fraction": 0.4545454545454442,
        "manifold_face_fraction": 0.9999999999999772,
        "edge_link_cycle_count": 4,
        "edge_link_candidate_count": 27,
        "edge_link_cycle_fraction": 0.14814814814814267,
        "edge_link_noncircle_cycle_count": 0,
        "K_mean": 0.5412193744434357,
        "K_p95": 1.1195013348643104,
        "closed_ratio": 0.5211607215454973,
        "exact_residual_ratio": 0.27778399954302363,
        "harmonic_ratio": 0.1289340693873014
      },
      "automatic_pairings_applied": 2,
      "automatic_pairing_attempts_logged": 2,
      "candidate_refinement_metrics": {
        "candidate_count_ok": 13,
        "candidate_count_beta2_opening": 9,
        "candidate_count_selected_by_rule": 2,
        "candidate_count_beta2_and_C_eigen_lock": 2,
        "exists_beta2_and_C_eigen_lock": true,
        "best_all_C_eigen_lock_mean": 0.10339126937405942,
        "best_all_C_eigen_lock_max": 0.10339126937406562,
        "best_all_delta_beta2": 2,
        "best_all_candidate_id": 32,
        "best_beta2_C_eigen_lock_mean": 0.10339126937405942,
        "best_beta2_C_eigen_lock_max": 0.10339126937406562,
        "best_beta2_candidate_id": 32,
        "best_beta2_selected_by_current_rule": false,
        "best_beta2_transport_cosine": -0.06977274777580166,
        "best_beta2_directed_imbalance": 0.7805782412610942,
        "best_beta2_transverse_complementarity": 0.33612090443309484,
        "best_beta2_comm_signed_birth_over_abs": -0.2723618631581503,
        "selected_C_eigen_lock_mean": 0.16875463166528093,
        "selected_C_eigen_lock_max": 0.16875463166528396,
        "selected_transport_cosine_mean": -0.07049986362874583,
        "beta2_transport_cosine_mean": 0.19227258836368494,
        "beta2_C_eigen_lock_mean_mean": 0.42737776224943186,
        "beta2_comm_signed_birth_over_abs_mean": -0.07227612539121557
      },
      "interpretation_flags": {
        "beta2_opened_by_current_rule": true,
        "exists_beta2_and_C_eigen_lock": true,
        "current_rule_missed_better_beta2_candidate": true,
        "decision_used_delta_beta_any": false
      }
    },
    {
      "variant": "no_backreaction",
      "variant_phase": "no_backreaction_phaseminus1",
      "phase_sign": -1,
      "max_level": 2,
      "source": "live",
      "baseline_metrics": {
        "vertices": 13,
        "edges": 33,
        "faces": 31,
        "tets": 10,
        "euler": 1,
        "beta0": 1,
        "beta1": 0,
        "beta2": 0,
        "beta3": 0,
        "boundary_faces": 22,
        "saturated_faces": 9,
        "overfull_faces": 0,
        "boundary_fraction": 0.7096774193548159,
        "saturated_fraction": 0.29032258064515193,
        "manifold_face_fraction": 0.9999999999999678,
        "edge_link_cycle_count": 0,
        "edge_link_candidate_count": 17,
        "edge_link_cycle_fraction": 0.0,
        "edge_link_noncircle_cycle_count": 0,
        "K_mean": 0.6243169724281119,
        "K_p95": 1.3870186003895344,
        "closed_ratio": 0.5081210545386275,
        "exact_residual_ratio": 0.2737836843813679,
        "harmonic_ratio": 0.0
      },
      "auto_metrics": {
        "vertices": 13,
        "edges": 38,
        "faces": 44,
        "tets": 16,
        "euler": 3,
        "beta0": 1,
        "beta1": 0,
        "beta2": 2,
        "beta3": 0,
        "boundary_faces": 24,
        "saturated_faces": 20,
        "overfull_faces": 0,
        "boundary_fraction": 0.545454545454533,
        "saturated_fraction": 0.4545454545454442,
        "manifold_face_fraction": 0.9999999999999772,
        "edge_link_cycle_count": 4,
        "edge_link_candidate_count": 27,
        "edge_link_cycle_fraction": 0.14814814814814267,
        "edge_link_noncircle_cycle_count": 0,
        "K_mean": 0.5412193744434357,
        "K_p95": 1.1195013348643104,
        "closed_ratio": 0.5211607215454973,
        "exact_residual_ratio": 0.27778399954302363,
        "harmonic_ratio": 0.1289340693873014
      },
      "automatic_pairings_applied": 2,
      "automatic_pairing_attempts_logged": 2,
      "candidate_refinement_metrics": {
        "candidate_count_ok": 13,
        "candidate_count_beta2_opening": 9,
        "candidate_count_selected_by_rule": 2,
        "candidate_count_beta2_and_C_eigen_lock": 4,
        "exists_beta2_and_C_eigen_lock": true,
        "best_all_C_eigen_lock_mean": 0.1544549595997748,
        "best_all_C_eigen_lock_max": 0.1544549595997853,
        "best_all_delta_beta2": 2,
        "best_all_candidate_id": 32,
        "best_beta2_C_eigen_lock_mean": 0.1544549595997748,
        "best_beta2_C_eigen_lock_max": 0.1544549595997853,
        "best_beta2_candidate_id": 32,
        "best_beta2_selected_by_current_rule": false,
        "best_beta2_transport_cosine": 0.30604077452731443,
        "best_beta2_directed_imbalance": 0.7805782412610942,
        "best_beta2_transverse_complementarity": 0.33612090443309484,
        "best_beta2_comm_signed_birth_over_abs": -0.26074189653167273,
        "selected_C_eigen_lock_mean": 0.18117912915543988,
        "selected_C_eigen_lock_max": 0.18117912915544102,
        "selected_transport_cosine_mean": 0.4487013824740501,
        "beta2_transport_cosine_mean": 0.2654988516572707,
        "beta2_C_eigen_lock_mean_mean": 0.3658958408602993,
        "beta2_comm_signed_birth_over_abs_mean": -0.0471277850107167
      },
      "interpretation_flags": {
        "beta2_opened_by_current_rule": true,
        "exists_beta2_and_C_eigen_lock": true,
        "current_rule_missed_better_beta2_candidate": true,
        "decision_used_delta_beta_any": false
      }
    }
  ]
}